install/_local_setup_util_sh.py
resource/scenario_execution
scenario_execution/__init__.py
scenario_execution/get_osc_library.py
scenario_execution/scenario_execution_base.py
scenario_execution/actions/__init__.py
scenario_execution/actions/base_action.py
scenario_execution/actions/base_action_subtree.py
scenario_execution/actions/compare.py
scenario_execution/actions/decrement.py
scenario_execution/actions/increment.py
scenario_execution/actions/log.py
scenario_execution/actions/run_process.py
scenario_execution/external_methods/__init__.py
scenario_execution/external_methods/common.py
scenario_execution/external_methods/random.py
scenario_execution/lib_osc/helpers.osc
scenario_execution/lib_osc/robotics.osc
scenario_execution/lib_osc/standard.osc
scenario_execution/lib_osc/types.osc
scenario_execution/model/__init__.py
scenario_execution/model/error.py
scenario_execution/model/external_interface.py
scenario_execution/model/model_base_visitor.py
scenario_execution/model/model_blackboard.py
scenario_execution/model/model_builder.py
scenario_execution/model/model_file_loader.py
scenario_execution/model/model_resolver.py
scenario_execution/model/model_to_py_tree.py
scenario_execution/model/osc2_parser.py
scenario_execution/model/types.py
scenario_execution/osc2_parsing/OpenSCENARIO2Lexer.py
scenario_execution/osc2_parsing/OpenSCENARIO2Listener.py
scenario_execution/osc2_parsing/OpenSCENARIO2Parser.py
scenario_execution/osc2_parsing/OpenSCENARIO2Visitor.py
scenario_execution/osc2_parsing/__init__.py
scenario_execution/utils/__init__.py
scenario_execution/utils/logging.py
scenario_execution-1.3.0.data/data/share/ament_index/resource_index/packages/scenario_execution
scenario_execution-1.3.0.data/data/share/scenario_execution/package.xml
scenario_execution-1.3.0.dist-info/METADATA
scenario_execution-1.3.0.dist-info/WHEEL
scenario_execution-1.3.0.dist-info/entry_points.txt
scenario_execution-1.3.0.dist-info/top_level.txt
scenario_execution-1.3.0.dist-info/zip-safe
scenario_execution-1.3.0.dist-info/RECORD
