Metadata-Version: 2.4
Name: scenario_execution
Version: 1.3.0
Summary: Scenario Execution for Robotics
Home-page: https://github.com/IntelLabs/scenario_execution
Maintainer: Frederik Pasch
Maintainer-email: fred-labs@mailbox.org
License: Apache License 2.0
Project-URL: Homepage, https://github.com/IntelLabs/scenario_execution
Project-URL: Documentation, https://github.com/IntelLabs/scenario_execution
Project-URL: Issues, https://github.com/IntelLabs/scenario_execution/issues
Classifier: Programming Language :: Python :: 3
Requires-Dist: setuptools
Requires-Dist: antlr4-python3-runtime==4.9.2
Requires-Dist: pyyaml==6.0.1
Requires-Dist: py-trees==2.3.0
Dynamic: classifier
Dynamic: description
Dynamic: description-content-type
Dynamic: home-page
Dynamic: license
Dynamic: maintainer
Dynamic: maintainer-email
Dynamic: project-url
Dynamic: requires-dist
Dynamic: summary
